setup.py
flask_abort/__init__.py
flask_abort.egg-info/PKG-INFO
flask_abort.egg-info/SOURCES.txt
flask_abort.egg-info/dependency_links.txt
flask_abort.egg-info/requires.txt
flask_abort.egg-info/top_level.txt