Metadata-Version: 1.0
Name: flask_abort
Version: 0.0.1
Summary: flask abort
Home-page: UNKNOWN
Author: UNKNOWN
Author-email: UNKNOWN
License: UNKNOWN
Platform: UNKNOWN
